Metadata-Version: 2.1
Name: DeepTextSearch
Version: 0.3
Summary: Deep Text Search is an AI-powered multilingual text search and recommendation engine with state-of-the-art transformer-based multilingual text embedding (50+ languages).
Home-page: https://github.com/TechyNilesh/DeepTextSearch
Author: Nilesh Verma
Author-email: me@nileshverma.com
License: MIT
Download-URL: https://github.com/TechyNilesh/DeepTextSearch/archive/refs/tags/v_03.tar.gz
Keywords: Deep Text Search Engine,AI Text search,Text Search Python,Text Recommendation Engine
Platform: UNKNOWN
Classifier: Development Status :: 4 - Beta
Classifier: Intended Audience :: Developers
Classifier: Topic :: Software Development :: Build Tools
Classifier: License :: OSI Approved :: MIT License
Classifier: Programming Language :: Python :: 3
Classifier: Programming Language :: Python :: 3.4
Classifier: Programming Language :: Python :: 3.5
Classifier: Programming Language :: Python :: 3.6
Classifier: Programming Language :: Python :: 3.7
Classifier: Programming Language :: Python :: 3.8
Classifier: Programming Language :: Python :: 3.9
License-File: LICENSE.txt
